{
    "Unloaded_capacity_derated_max":  36552,
    "todayForecastPeakDemand":  29172,
    "Unloaded_capacity_1H":  8794,
    "Shutdown":  "2501.37",
    "currentRenewablesHybrid":  null,
    "CurrentSystemDemandWithoutPump":  19000,
    "Required_reserve":  1444,
    "currentCoalCO2":  2,
    "Current_reserve":  2528,
    "currentBiomassCO2":  77,
    "currentOther":  0,
    "HistoryFirstDate":  "20180410",
    "currentNuclear":  2273,
    "currentGeothermal":  932,
    "tomorrowsForecastPeakDemand":  30015,
    "Limitation":  "2990.98",
    "currentSolar":  14286,
    "TodaysPeakDemandTS":  "20230426075612",
    "currentImports":  -1936,
    "currentNaturalGasCO2":  2826,
    "CurrentAdjustedUnloadedGenerationCapacityTS":  "20230426112457",
    "currentBiogasCO2":  104,
    "currentSolarHybrids":  737,
    "Unloaded_capacity_10M":  5674,
    "currentRenewables":  17289,
    "currentWindHybrids":  -1,
    "currentCo2":  2289,
    "currentImportsCO2":  -822,
    "CurrentSystemDemandWithoutPumpTS":  "20230426112411",
    "Available_capacity":  27874,
    "todayForecastPeakDemandTS":  "20230426204500",
    "currentLargeHydro":  1921,
    "CurrentNetDemandWithoutPumpTS":  "20230426112411",
    "CurrentNetDemandWithoutPump":  4058,
    "hybridsPercent":  2.6,
    "currentWind":  1424,
    "currentGeothermalCO2":  9,
    "CurrentSystemDemand":  22200,
    "currentBiomass":  180,
    "currentNonRenewableHybrid":  null,
    "CurrentSystemDemandTS":  "20230426112456",
    "currentNaturalGas":  6481,
    "histDemand":  "52,061 MW",
    "histDemandDate":  "Sep 6, 2022",
    "CurrentAdjustedUnloadedGenerationCapacity":  15893,
    "CurrentSystemDemandPlusUnloaded4h":  36100,
    "gridstatus":  [
                       "Normal"
                   ],
    "slotDate":  "04/26/2023 11:25",
    "renewablesPercentwoBatteries":  78,
    "currentBatteriesStandalone":  -1952,
    "currentCoal":  3,
    "currentBiogas":  202,
    "currentBatteriesHybrid":  -172,
    "currentSmallHydro":  325,
    "AvailableCapacity":  38093,
    "currentHybrids":  568,
    "PS_VERSION":  "1.26b",
    "Unloaded_capacity_4H":  13900,
    "renewablesPercent":  78,
    "CurrentNetDemand":  7242,
    "currentBatteries":  -2120,
    "CurrentNetDemandTS":  "20230426112411",
    "OutageDTS":  "07/17/2019 23:30:00 (PPT)",
    "currentRenewableswoBatteries":  17289,
    "currentCo2intensity":  0.1031229073959100555095619771,
    "TodaysPeakDemand":  24682
}
