{
    "todayForecastPeakDemandTS": "20210315194500",
    "AvailableCapacity": 41412,
    "currentWind": 4640,
    "Limitation": 0,
    "CurrentSystemDemandWithoutPump": 25639,
    "histDemand": "50,270 MW",
    "TodaysPeakDemand": 26134,
    "slotDate": "03/15/2021 09:45",
    "gridstatus": [
        "Normal"
    ],
    "currentCo2intensity": 0.21317357199746317,
    "CurrentNetDemandWithoutPump": 14118,
    "histDemandDate": "Jul 24, 2006",
    "CurrentNetDemand": 14457,
    "CurrentSystemDemand": 25940,
    "Shutdown": 0,
    "HistoryFirstDate": "20180410",
    "CurrentAdjustedUnloadedGenerationCapacityTS": "20210315094452",
    "CurrentSystemDemandWithoutPumpTS": "20210315094411",
    "currentRenewableswoBatteries": 13125,
    "TodaysPeakDemandTS": "20210315093900",
    "currentRenewables": 13190,
    "CurrentNetDemandTS": "20210315094411",
    "CurrentAdjustedUnloadedGenerationCapacity": 15472,
    "renewablesPercent": 51,
    "CurrentNetDemandWithoutPumpTS": "20210315094411",
    "tomorrowsForecastPeakDemand": 26925,
    "PS_VERSION": "1.26b",
    "CurrentSystemDemandTS": null,
    "currentSolar": 6817,
    "renewablesPercentwoBatteries": 51,
    "OutageDTS": null,
    "currentCo2": 5530,
    "todayForecastPeakDemand": 27820
}
