{
    "CurrentNetDemandWithoutPumpTS": "20221130125411",
    "slotDate": "11/30/2022 12:55",
    "renewablesPercentwoBatteries": 54,
    "histDemand": "52,061 MW",
    "CurrentSystemDemandWithoutPumpTS": "20221130125411",
    "Unloaded_capacity_derated_max": 35901,
    "histDemandDate": "Sep 08, 2022",
    "Required_reserve": 1404,
    "CurrentSystemDemandTS": "20221130125456",
    "TodaysPeakDemandTS": "20221130072052",
    "Unloaded_capacity_4H": 18324,
    "Unloaded_capacity_10M": 8646,
    "currentRenewables": 13739,
    "Limitation": "2990.98",
    "PS_VERSION": "1.26b",
    "AvailableCapacity": 43457,
    "renewablesPercent": 58,
    "CurrentAdjustedUnloadedGenerationCapacityTS": "20221130125456",
    "todayForecastPeakDemandTS": "20221130174500",
    "currentCo2intensity": 0.2007577401175608,
    "todayForecastPeakDemand": 28494,
    "currentSolar": 10241,
    "CurrentSystemDemand": 23588,
    "currentCo2": 4735,
    "CurrentAdjustedUnloadedGenerationCapacity": 19869,
    "OutageDTS": "07/17/2019 23:30:00 (PPT)",
    "HistoryFirstDate": "20180410",
    "Available_capacity": 32233,
    "CurrentNetDemandWithoutPump": 10652,
    "CurrentSystemDemandPlusUnloaded4h": 41912,
    "Shutdown": "2501.37",
    "Unloaded_capacity_1H": 12992,
    "TodaysPeakDemand": 27088,
    "currentWind": 896,
    "tomorrowsForecastPeakDemand": 29132.0,
    "CurrentNetDemandTS": "20221130125411",
    "CurrentNetDemand": 12442,
    "currentRenewableswoBatteries": 12631,
    "gridstatus": [
        "Normal"
    ],
    "Current_reserve": 1822,
    "CurrentSystemDemandWithoutPump": 21821
}
