{
    "Unloaded_capacity_derated_max":  30731,
    "todayForecastPeakDemand":  25681,
    "Unloaded_capacity_1H":  8494,
    "Shutdown":  "2501.37",
    "currentRenewablesHybrid":  null,
    "CurrentSystemDemandWithoutPump":  25445,
    "Required_reserve":  1450,
    "currentCoalCO2":  2,
    "Current_reserve":  2281,
    "currentBiomassCO2":  91,
    "currentOther":  0.0,
    "HistoryFirstDate":  "20180410",
    "currentNuclear":  1595,
    "currentGeothermal":  942,
    "tomorrowsForecastPeakDemand":  24578,
    "Limitation":  "2990.98",
    "currentSolar":  -42,
    "TodaysPeakDemandTS":  "20230311193540",
    "currentImports":  5431,
    "currentNaturalGasCO2":  4694,
    "CurrentAdjustedUnloadedGenerationCapacityTS":  "20230311194009",
    "currentBiogasCO2":  108,
    "currentSolarHybrids":  -3,
    "Unloaded_capacity_10M":  5275,
    "currentRenewables":  4397,
    "currentWindHybrids":  2,
    "currentCo2":  7066,
    "currentImportsCO2":  2457,
    "CurrentSystemDemandWithoutPumpTS":  "20230311193811",
    "Available_capacity":  30761,
    "todayForecastPeakDemandTS":  "20230311184500",
    "currentLargeHydro":  2726,
    "CurrentNetDemandWithoutPumpTS":  "20230311193811",
    "CurrentNetDemandWithoutPump":  22745,
    "hybridsPercent":  1.0,
    "currentWind":  2791,
    "currentGeothermalCO2":  9,
    "CurrentSystemDemand":  25486,
    "currentBiomass":  206,
    "currentNonRenewableHybrid":  null,
    "CurrentSystemDemandTS":  "20230311193956",
    "currentNaturalGas":  10585,
    "histDemand":  "50,270 MW",
    "histDemandDate":  "Jul 24, 2006",
    "CurrentAdjustedUnloadedGenerationCapacity":  14913,
    "CurrentSystemDemandPlusUnloaded4h":  37129,
    "gridstatus":  [
                       "Normal"
                   ],
    "slotDate":  "03/11/2023 19:40",
    "renewablesPercentwoBatteries":  17,
    "currentBatteriesStandalone":  2148,
    "currentCoal":  3,
    "currentBiogas":  205,
    "currentBatteriesHybrid":  246,
    "currentSmallHydro":  244,
    "AvailableCapacity":  40399,
    "currentHybrids":  245,
    "PS_VERSION":  "1.26b",
    "Unloaded_capacity_4H":  11643,
    "renewablesPercent":  17,
    "CurrentNetDemand":  23311,
    "currentBatteries":  2800,
    "CurrentNetDemandTS":  "20230311193811",
    "OutageDTS":  "07/17/2019 23:30:00 (PPT)",
    "currentRenewableswoBatteries":  4397,
    "currentCo2intensity":  0.2772710996991509357599949201,
    "TodaysPeakDemand":  26066
}
