{
    "todayForecastPeakDemandTS":  "20210703183000",
    "AvailableCapacity":  42974,
    "currentWind":  1298,
    "Limitation":  0,
    "CurrentSystemDemandWithoutPump":  24254,
    "histDemand":  "50,270 MW",
    "TodaysPeakDemand":  28241,
    "slotDate":  "07/03/2021 09:30",
    "gridstatus":  [
                       "Normal"
                   ],
    "currentCo2intensity":  0.23529545607991656,
    "CurrentNetDemandWithoutPump":  13831,
    "histDemandDate":  "Jul 24, 2006",
    "CurrentNetDemand":  15220,
    "CurrentSystemDemand":  25580,
    "Shutdown":  0,
    "HistoryFirstDate":  "20180410",
    "CurrentAdjustedUnloadedGenerationCapacityTS":  "20210703092956",
    "CurrentSystemDemandWithoutPumpTS":  "20210703092811",
    "currentRenewableswoBatteries":  12098,
    "TodaysPeakDemandTS":  "20210703000120",
    "currentRenewables":  12883,
    "CurrentNetDemandTS":  "20210703092811",
    "CurrentAdjustedUnloadedGenerationCapacity":  17394,
    "renewablesPercent":  50,
    "CurrentNetDemandWithoutPumpTS":  "20210703092811",
    "tomorrowsForecastPeakDemand":  33501,
    "PS_VERSION":  "1.26b",
    "CurrentSystemDemandTS":  null,
    "currentSolar":  9130,
    "renewablesPercentwoBatteries":  47,
    "OutageDTS":  null,
    "currentCo2":  6019,
    "todayForecastPeakDemand":  34411
}
