{
    "todayForecastPeakDemandTS":  "20210713174500",
    "AvailableCapacity":  50982,
    "currentWind":  1852,
    "Limitation":  0,
    "CurrentSystemDemandWithoutPump":  34584,
    "histDemand":  "50,270 MW",
    "TodaysPeakDemand":  34913,
    "slotDate":  "07/13/2021 13:55",
    "gridstatus":  [
                       "Normal"
                   ],
    "currentCo2intensity":  0.22061995330596665,
    "CurrentNetDemandWithoutPump":  21014,
    "histDemandDate":  "Jul 24, 2006",
    "CurrentNetDemand":  21388,
    "CurrentSystemDemand":  34838,
    "Shutdown":  0,
    "HistoryFirstDate":  "20180410",
    "CurrentAdjustedUnloadedGenerationCapacityTS":  "20210713135456",
    "CurrentSystemDemandWithoutPumpTS":  "20210713135411",
    "currentRenewableswoBatteries":  15186,
    "TodaysPeakDemandTS":  "20210713135408",
    "currentRenewables":  15512,
    "CurrentNetDemandTS":  "20210713135411",
    "CurrentAdjustedUnloadedGenerationCapacity":  16144,
    "renewablesPercent":  45,
    "CurrentNetDemandWithoutPumpTS":  "20210713135411",
    "tomorrowsForecastPeakDemand":  37591,
    "PS_VERSION":  "1.26b",
    "CurrentSystemDemandTS":  null,
    "currentSolar":  11668,
    "renewablesPercentwoBatteries":  44,
    "OutageDTS":  null,
    "currentCo2":  7686,
    "todayForecastPeakDemand":  38524
}
