{
    "todayForecastPeakDemandTS": "20210812174500",
    "AvailableCapacity": 53337,
    "currentWind": 2051,
    "Limitation": 0,
    "CurrentSystemDemandWithoutPump": 31018,
    "histDemand": "50,270 MW",
    "TodaysPeakDemand": 31869,
    "slotDate": "08/12/2021 10:25",
    "gridstatus": [
        "Normal"
    ],
    "currentCo2intensity": 0.22852274748507648,
    "CurrentNetDemandWithoutPump": 18356,
    "histDemandDate": "Jul 24, 2006",
    "CurrentNetDemand": 19350,
    "CurrentSystemDemand": 31861,
    "Shutdown": 0,
    "HistoryFirstDate": "20180410",
    "CurrentAdjustedUnloadedGenerationCapacityTS": "20210812102456",
    "CurrentSystemDemandWithoutPumpTS": "20210812102411",
    "currentRenewableswoBatteries": 14129,
    "TodaysPeakDemandTS": "20210812101700",
    "currentRenewables": 14408,
    "CurrentNetDemandTS": "20210812102411",
    "CurrentAdjustedUnloadedGenerationCapacity": 21476,
    "renewablesPercent": 45,
    "CurrentNetDemandWithoutPumpTS": "20210812102411",
    "tomorrowsForecastPeakDemand": 40178,
    "PS_VERSION": "1.26b",
    "CurrentSystemDemandTS": null,
    "currentSolar": 10507,
    "renewablesPercentwoBatteries": 44,
    "OutageDTS": null,
    "currentCo2": 7281,
    "todayForecastPeakDemand": 42355
}
