{
    "Unloaded_capacity_derated_max":  33070,
    "todayForecastPeakDemand":  26357,
    "Unloaded_capacity_1H":  10588,
    "Shutdown":  "2501.37",
    "currentRenewablesHybrid":  null,
    "CurrentSystemDemandWithoutPump":  20459,
    "Required_reserve":  1189,
    "currentCoalCO2":  0.0,
    "Current_reserve":  1658,
    "currentBiomassCO2":  112,
    "currentOther":  0,
    "HistoryFirstDate":  "20180410",
    "currentNuclear":  2261,
    "currentGeothermal":  795,
    "tomorrowsForecastPeakDemand":  26364,
    "Limitation":  "2990.98",
    "currentSolar":  -16,
    "TodaysPeakDemandTS":  "20240228000036",
    "currentImports":  5912,
    "currentNaturalGasCO2":  3127,
    "CurrentAdjustedUnloadedGenerationCapacityTS":  "20240228012456",
    "currentBiogasCO2":  105,
    "currentSolarHybrids":  -3,
    "Unloaded_capacity_10M":  6689,
    "currentRenewables":  2426,
    "currentWindHybrids":  0.0,
    "currentCo2":  6008,
    "currentImportsCO2":  2634,
    "CurrentSystemDemandWithoutPumpTS":  "20240228012411",
    "Available_capacity":  27485,
    "todayForecastPeakDemandTS":  "20240228184500",
    "currentLargeHydro":  3215,
    "CurrentNetDemandWithoutPumpTS":  "20240228012411",
    "CurrentNetDemandWithoutPump":  19625,
    "hybridsPercent":  -0.1,
    "currentWind":  883,
    "currentGeothermalCO2":  8,
    "CurrentSystemDemand":  20795,
    "currentBiomass":  251,
    "currentNonRenewableHybrid":  null,
    "CurrentSystemDemandTS":  "20240228012456",
    "currentNaturalGas":  6961,
    "histDemand":  "52,061 MW",
    "histDemandDate":  "Sep 6, 2022",
    "CurrentAdjustedUnloadedGenerationCapacity":  19065,
    "CurrentSystemDemandPlusUnloaded4h":  39154,
    "gridstatus":  [
                       "Normal"
                   ],
    "slotDate":  "02/28/2024 01:25",
    "renewablesPercentwoBatteries":  12,
    "currentBatteriesStandalone":  -211,
    "currentCoal":  0.0,
    "currentBiogas":  197,
    "currentBatteriesHybrid":  -6,
    "currentSmallHydro":  279,
    "AvailableCapacity":  39860,
    "currentHybrids":  -11,
    "PS_VERSION":  "1.26b",
    "Unloaded_capacity_4H":  18359,
    "renewablesPercent":  12,
    "CurrentNetDemand":  19921,
    "currentBatteries":  -226,
    "CurrentNetDemandTS":  "20240228012411",
    "OutageDTS":  "07/17/2019 23:30:00 (PPT)",
    "currentRenewableswoBatteries":  2426,
    "currentCo2intensity":  0.2889149471781742127350930406,
    "TodaysPeakDemand":  21853
}
