{
    "CurrentNetDemandWithoutPumpTS": "20220216035811",
    "slotDate": "02/16/2022 04:00",
    "renewablesPercentwoBatteries": 28,
    "histDemand": "50,270 MW",
    "CurrentSystemDemandWithoutPumpTS": "20220216035811",
    "Available_capacity": 28095,
    "histDemandDate": "Jul 24, 2006",
    "Required_reserve": 1604,
    "CurrentSystemDemandTS": "20220216035956",
    "TodaysPeakDemandTS": "20220216000128",
    "Unloaded_capacity_4H": 13464,
    "Unloaded_capacity_10M": 7318,
    "currentRenewables": 5847,
    "Limitation": "2990.98",
    "PS_VERSION": "1.26b",
    "AvailableCapacity": 37146,
    "renewablesPercent": 28,
    "CurrentAdjustedUnloadedGenerationCapacityTS": "20220216035956",
    "todayForecastPeakDemandTS": "20220216184500",
    "currentCo2intensity": 0.29869091756594973,
    "todayForecastPeakDemand": 27030,
    "currentSolar": -46,
    "CurrentSystemDemand": 20777,
    "currentCo2": 6206,
    "CurrentAdjustedUnloadedGenerationCapacity": 16369,
    "OutageDTS": "07/17/2019 23:30:00 (PPT)",
    "HistoryFirstDate": "20180410",
    "CurrentNetDemandWithoutPump": 16336,
    "Shutdown": "2501.37",
    "Unloaded_capacity_1H": 11905,
    "Unloaded_capacity_derated_nax": 37562,
    "TodaysPeakDemand": 21896,
    "currentWind": 4255,
    "tomorrowsForecastPeakDemand": 27057,
    "CurrentNetDemandTS": "20220216035811",
    "CurrentNetDemand": 16505,
    "currentRenewableswoBatteries": 5731,
    "gridstatus": [
        "Normal"
    ],
    "Current_reserve": 2068,
    "CurrentSystemDemandWithoutPump": 20562
}
