{
    "CurrentNetDemandWithoutPumpTS": "20220710163411",
    "slotDate": "07/10/2022 16:35",
    "renewablesPercentwoBatteries": 45,
    "histDemand": "50,270 MW",
    "CurrentSystemDemandWithoutPumpTS": "20220710163411",
    "Unloaded_capacity_derated_max": 29155,
    "histDemandDate": "Jul 24, 2006",
    "Required_reserve": 1976,
    "CurrentSystemDemandTS": "20220710163456",
    "TodaysPeakDemandTS": "20220710163312",
    "Unloaded_capacity_4H": 17376,
    "Unloaded_capacity_10M": 8532,
    "currentRenewables": 14811,
    "Limitation": "2990.98",
    "PS_VERSION": "1.26b",
    "AvailableCapacity": 54093,
    "renewablesPercent": 44,
    "CurrentAdjustedUnloadedGenerationCapacityTS": "20220710163456",
    "todayForecastPeakDemandTS": "20220710183000",
    "currentCo2intensity": 0.18906306263463127,
    "todayForecastPeakDemand": 35816,
    "currentSolar": 12229,
    "CurrentSystemDemand": 33550,
    "currentCo2": 6343,
    "CurrentAdjustedUnloadedGenerationCapacity": 20543,
    "OutageDTS": "07/17/2019 23:30:00 (PPT)",
    "HistoryFirstDate": "20180410",
    "Available_capacity": 42082,
    "CurrentNetDemandWithoutPump": 19975,
    "CurrentSystemDemandPlusUnloaded4h": 50926,
    "Shutdown": "2501.37",
    "Unloaded_capacity_1H": 13635,
    "TodaysPeakDemand": 33559,
    "currentWind": 1230,
    "tomorrowsForecastPeakDemand": 40742.0,
    "CurrentNetDemandTS": "20220710163411",
    "CurrentNetDemand": 20160,
    "currentRenewableswoBatteries": 15140,
    "gridstatus": [
        "Normal"
    ],
    "Current_reserve": 2476,
    "CurrentSystemDemandWithoutPump": 33433
}
