{
    "Unloaded_capacity_derated_max":  27193,
    "todayForecastPeakDemand":  27079,
    "Unloaded_capacity_1H":  10309,
    "Shutdown":  "2501.37",
    "currentRenewablesHybrid":  null,
    "CurrentSystemDemandWithoutPump":  26896,
    "Required_reserve":  1550,
    "currentCoalCO2":  0,
    "Current_reserve":  2250,
    "currentBiomassCO2":  138,
    "currentOther":  0,
    "HistoryFirstDate":  "20180410",
    "currentNuclear":  2231,
    "currentGeothermal":  659,
    "tomorrowsForecastPeakDemand":  29058,
    "Limitation":  "2990.98",
    "currentSolar":  -56,
    "TodaysPeakDemandTS":  "20231217173816",
    "currentImports":  3528,
    "currentNaturalGasCO2":  6055,
    "CurrentAdjustedUnloadedGenerationCapacityTS":  "20231217173957",
    "currentBiogasCO2":  104,
    "currentSolarHybrids":  -2,
    "Unloaded_capacity_10M":  6513,
    "currentRenewables":  2244,
    "currentWindHybrids":  0.0,
    "currentCo2":  7817,
    "currentImportsCO2":  1529,
    "CurrentSystemDemandWithoutPumpTS":  "20231217173811",
    "Available_capacity":  33484,
    "todayForecastPeakDemandTS":  "20231217173000",
    "currentLargeHydro":  2553,
    "CurrentNetDemandWithoutPumpTS":  "20231217173811",
    "CurrentNetDemandWithoutPump":  26055,
    "hybridsPercent":  0.6,
    "currentWind":  881,
    "currentGeothermalCO2":  6,
    "CurrentSystemDemand":  26971,
    "currentBiomass":  316,
    "currentNonRenewableHybrid":  null,
    "CurrentSystemDemandTS":  "20231217173956",
    "currentNaturalGas":  13865,
    "histDemand":  "52,061 MW",
    "histDemandDate":  "Sep 6, 2022",
    "CurrentAdjustedUnloadedGenerationCapacity":  19470,
    "CurrentSystemDemandPlusUnloaded4h":  43208,
    "gridstatus":  [
                       "Normal"
                   ],
    "slotDate":  "12/17/2023 17:40",
    "renewablesPercentwoBatteries":  8,
    "currentBatteriesStandalone":  1939,
    "currentCoal":  0,
    "currentBiogas":  200,
    "currentBatteriesHybrid":  145,
    "currentSmallHydro":  269,
    "AvailableCapacity":  46441,
    "currentHybrids":  163,
    "PS_VERSION":  "1.26b",
    "Unloaded_capacity_4H":  16237,
    "renewablesPercent":  8,
    "CurrentNetDemand":  26172,
    "currentBatteries":  2051,
    "CurrentNetDemandTS":  "20231217173811",
    "OutageDTS":  "07/17/2019 23:30:00 (PPT)",
    "currentRenewableswoBatteries":  2244,
    "currentCo2intensity":  0.2898390757154503442676523514,
    "TodaysPeakDemand":  26987
}
