{
    "Unloaded_capacity_derated_max": 37605,
    "todayForecastPeakDemand": 25238,
    "Unloaded_capacity_1H": 10188,
    "Shutdown": "2501.37",
    "currentRenewablesHybrid": null,
    "CurrentSystemDemandWithoutPump": 16186,
    "Required_reserve": 1320,
    "currentCoalCO2": 0.0,
    "Current_reserve": 3504,
    "currentBiomassCO2": 102,
    "currentOther": 0,
    "HistoryFirstDate": "20180410",
    "currentNuclear": 2263,
    "currentGeothermal": 742,
    "tomorrowsForecastPeakDemand": 23550,
    "Limitation": "2990.98",
    "currentSolar": 13311,
    "TodaysPeakDemandTS": "20240308065752",
    "currentImports": -3006,
    "currentNaturalGasCO2": 1614,
    "CurrentAdjustedUnloadedGenerationCapacityTS": "20240308113456",
    "currentBiogasCO2": 100,
    "currentSolarHybrids": 1121,
    "Unloaded_capacity_10M": 7559,
    "currentRenewables": 15953,
    "currentWindHybrids": 0.0,
    "currentCo2": 562,
    "currentImportsCO2": -1318,
    "CurrentSystemDemandWithoutPumpTS": "20240308113411",
    "Available_capacity": 27284,
    "todayForecastPeakDemandTS": "20240308184500",
    "currentLargeHydro": 1346,
    "CurrentNetDemandWithoutPumpTS": "20240308113411",
    "CurrentNetDemandWithoutPump": 2836,
    "hybridsPercent": 4.0,
    "currentWind": 1239,
    "currentGeothermalCO2": 7,
    "CurrentSystemDemand": 19725,
    "currentBiomass": 232,
    "currentNonRenewableHybrid": null,
    "CurrentSystemDemandTS": "20240308113456",
    "currentNaturalGas": 3691,
    "histDemand": "52,061 MW",
    "histDemandDate": "Sep 6, 2022",
    "CurrentAdjustedUnloadedGenerationCapacity": 21097,
    "CurrentSystemDemandPlusUnloaded4h": 38326,
    "gridstatus": [
        "Normal"
    ],
    "slotDate": "03/08/2024 11:35",
    "renewablesPercentwoBatteries": 81,
    "currentBatteriesStandalone": -3285,
    "currentCoal": 0.0,
    "currentBiogas": 190,
    "currentBatteriesHybrid": -303,
    "currentSmallHydro": 289,
    "AvailableCapacity": 40822,
    "currentHybrids": 796,
    "PS_VERSION": "1.26b",
    "Unloaded_capacity_4H": 18601,
    "renewablesPercent": 81,
    "CurrentNetDemand": 6270,
    "currentBatteries": -3554,
    "CurrentNetDemandTS": "20240308113411",
    "OutageDTS": "07/17/2019 23:30:00 (PPT)",
    "currentRenewableswoBatteries": 15953,
    "currentCo2intensity": 0.028483567712199717,
    "TodaysPeakDemand": 24608
}
