{
    "CurrentNetDemandWithoutPumpTS": "20220302065411",
    "slotDate": "03/02/2022 06:55",
    "renewablesPercentwoBatteries": 12,
    "histDemand": "50,270 MW",
    "CurrentSystemDemandWithoutPumpTS": "20220302065411",
    "Available_capacity": 31574,
    "histDemandDate": "Jul 24, 2006",
    "Required_reserve": 2366,
    "CurrentSystemDemandTS": "20220302065456",
    "TodaysPeakDemandTS": "20220302065004",
    "Unloaded_capacity_4H": 11405,
    "Unloaded_capacity_10M": 7499,
    "currentRenewables": 2818,
    "Limitation": "2990.98",
    "PS_VERSION": "1.26b",
    "AvailableCapacity": 39197,
    "renewablesPercent": 12,
    "CurrentAdjustedUnloadedGenerationCapacityTS": "20220302065456",
    "todayForecastPeakDemandTS": "20220302183000",
    "currentCo2intensity": 0.3246638015961882,
    "todayForecastPeakDemand": 28191,
    "currentSolar": 1159,
    "CurrentSystemDemand": 24075,
    "currentCo2": 7816,
    "CurrentAdjustedUnloadedGenerationCapacity": 15122,
    "OutageDTS": "07/17/2019 23:30:00 (PPT)",
    "HistoryFirstDate": "20180410",
    "CurrentNetDemandWithoutPump": 22087,
    "Shutdown": "2501.37",
    "Unloaded_capacity_1H": 10539,
    "Unloaded_capacity_derated_nax": 31992,
    "TodaysPeakDemand": 24210,
    "currentWind": 282,
    "tomorrowsForecastPeakDemand": 27647,
    "CurrentNetDemandTS": "20220302065411",
    "CurrentNetDemand": 22140,
    "currentRenewableswoBatteries": 2842,
    "gridstatus": [
        "Normal"
    ],
    "Current_reserve": 3185,
    "CurrentSystemDemandWithoutPump": 24013
}
