{
    "todayForecastPeakDemandTS": "20210406200000",
    "AvailableCapacity": 38832,
    "currentWind": 4389,
    "Limitation": 0,
    "CurrentSystemDemandWithoutPump": 26824,
    "histDemand": "50,270 MW",
    "TodaysPeakDemand": 26855,
    "slotDate": "04/06/2021 20:05",
    "gridstatus": [
        "Normal"
    ],
    "currentCo2intensity": 0.3145123972437905,
    "CurrentNetDemandWithoutPump": 22453,
    "histDemandDate": "Jul 24, 2006",
    "CurrentNetDemand": 22460,
    "CurrentSystemDemand": 26855,
    "Shutdown": 0,
    "HistoryFirstDate": "20180410",
    "CurrentAdjustedUnloadedGenerationCapacityTS": "20210406200456",
    "CurrentSystemDemandWithoutPumpTS": "20210406200411",
    "currentRenewableswoBatteries": 6030,
    "TodaysPeakDemandTS": "20210406200456",
    "currentRenewables": 5890,
    "CurrentNetDemandTS": "20210406200411",
    "CurrentAdjustedUnloadedGenerationCapacity": 11977,
    "renewablesPercent": 22,
    "CurrentNetDemandWithoutPumpTS": "20210406200411",
    "tomorrowsForecastPeakDemand": 26559,
    "PS_VERSION": "1.26b",
    "CurrentSystemDemandTS": null,
    "currentSolar": -45,
    "renewablesPercentwoBatteries": 22,
    "OutageDTS": null,
    "currentCo2": 8446,
    "todayForecastPeakDemand": 26898
}
