{
    "CurrentNetDemandWithoutPumpTS":  "20211103002811",
    "slotDate":  "11/03/2021 00:30",
    "renewablesPercentwoBatteries":  9,
    "histDemand":  "50,270 MW",
    "CurrentSystemDemandWithoutPumpTS":  "20211103002811",
    "Available_capacity":  27469,
    "histDemandDate":  "Jul 24, 2006",
    "Required_reserve":  1184,
    "CurrentSystemDemandTS":  "20211103002956",
    "TodaysPeakDemandTS":  "20211103000700",
    "Unloaded_capacity_4H":  10743,
    "Unloaded_capacity_10M":  6245,
    "currentRenewables":  2054,
    "Limitation":  "2990.98",
    "PS_VERSION":  "1.26b",
    "AvailableCapacity":  36177,
    "renewablesPercent":  10,
    "CurrentAdjustedUnloadedGenerationCapacityTS":  "20211103002956",
    "todayForecastPeakDemandTS":  "20211103183000",
    "currentCo2intensity":  0.360271029990298289605839291,
    "todayForecastPeakDemand":  28608,
    "currentSolar":  -34,
    "CurrentSystemDemand":  21223,
    "currentCo2":  7646,
    "CurrentAdjustedUnloadedGenerationCapacity":  14954,
    "OutageDTS":  "07/17/2019 23:30:00 (PPT)",
    "HistoryFirstDate":  "20180410",
    "CurrentNetDemandWithoutPump":  20717,
    "Shutdown":  "2501.37",
    "Unloaded_capacity_1H":  9491,
    "Unloaded_capacity_derated_nax":  31799,
    "TodaysPeakDemand":  21539,
    "currentWind":  350,
    "tomorrowsForecastPeakDemand":  28806,
    "CurrentNetDemandTS":  "20211103002811",
    "CurrentNetDemand":  20919,
    "currentRenewableswoBatteries":  1990,
    "gridstatus":  [
                       "Normal"
                   ],
    "Current_reserve":  1552,
    "CurrentSystemDemandWithoutPump":  20975
}
