{
    "todayForecastPeakDemandTS":  "20210816174500",
    "AvailableCapacity":  57081,
    "currentWind":  2606,
    "Limitation":  "2990.98",
    "CurrentSystemDemandWithoutPump":  41609,
    "histDemand":  "50,270 MW",
    "TodaysPeakDemand":  41693,
    "slotDate":  "08/16/2021 15:40",
    "gridstatus":  [
                       "Restricted Maintenance Operations"
                   ],
    "currentCo2intensity":  0.2467885626282727,
    "CurrentNetDemandWithoutPump":  28593,
    "histDemandDate":  "Jul 24, 2006",
    "CurrentNetDemand":  28684,
    "CurrentSystemDemand":  41693,
    "Shutdown":  "2501.37",
    "HistoryFirstDate":  "20180410",
    "CurrentAdjustedUnloadedGenerationCapacityTS":  "20210816153956",
    "CurrentSystemDemandWithoutPumpTS":  "20210816153811",
    "currentRenewableswoBatteries":  14530,
    "TodaysPeakDemandTS":  "20210816153956",
    "currentRenewables":  14481,
    "CurrentNetDemandTS":  "20210816153811",
    "CurrentAdjustedUnloadedGenerationCapacity":  15388,
    "renewablesPercent":  35,
    "CurrentNetDemandWithoutPumpTS":  "20210816153811",
    "tomorrowsForecastPeakDemand":  39355,
    "PS_VERSION":  "1.26b",
    "CurrentSystemDemandTS":  null,
    "currentSolar":  10358,
    "renewablesPercentwoBatteries":  35,
    "OutageDTS":  "07/17/2019 23:30:00 (PPT)",
    "currentCo2":  10289,
    "todayForecastPeakDemand":  43003
}
