{
    "CurrentNetDemandWithoutPumpTS":  "20220304151811",
    "slotDate":  "03/04/2022 15:20",
    "renewablesPercentwoBatteries":  64,
    "histDemand":  "50,270 MW",
    "CurrentSystemDemandWithoutPumpTS":  "20220304151811",
    "Available_capacity":  30475,
    "histDemandDate":  "Jul 24, 2006",
    "Required_reserve":  1373,
    "CurrentSystemDemandTS":  "20220304151956",
    "TodaysPeakDemandTS":  "20220304073304",
    "Unloaded_capacity_4H":  12569,
    "Unloaded_capacity_10M":  7820,
    "currentRenewables":  14589,
    "Limitation":  "2990.98",
    "PS_VERSION":  "1.26b",
    "AvailableCapacity":  40668,
    "renewablesPercent":  64,
    "CurrentAdjustedUnloadedGenerationCapacityTS":  "20220304151956",
    "todayForecastPeakDemandTS":  "20220304183000",
    "currentCo2intensity":  0.1372760781133519686752796249,
    "todayForecastPeakDemand":  26669,
    "currentSolar":  7037,
    "CurrentSystemDemand":  22654,
    "currentCo2":  3110,
    "CurrentAdjustedUnloadedGenerationCapacity":  18014,
    "OutageDTS":  "07/17/2019 23:30:00 (PPT)",
    "HistoryFirstDate":  "20180410",
    "CurrentNetDemandWithoutPump":  9075,
    "Shutdown":  "2501.37",
    "Unloaded_capacity_1H":  11533,
    "Unloaded_capacity_derated_nax":  37278,
    "TodaysPeakDemand":  24988,
    "currentWind":  6163,
    "tomorrowsForecastPeakDemand":  25183,
    "CurrentNetDemandTS":  "20220304151811",
    "CurrentNetDemand":  9619,
    "currentRenewableswoBatteries":  14586,
    "gridstatus":  [
                       "Normal"
                   ],
    "Current_reserve":  1749,
    "CurrentSystemDemandWithoutPump":  22165
}
