{
    "CurrentNetDemandWithoutPumpTS": "20220129051811",
    "slotDate": "01/29/2022 05:20",
    "renewablesPercentwoBatteries": 15,
    "histDemand": "50,270 MW",
    "CurrentSystemDemandWithoutPumpTS": "20220129051811",
    "Available_capacity": 29853,
    "histDemandDate": "Jul 24, 2006",
    "Required_reserve": 2118,
    "CurrentSystemDemandTS": "20220129051956",
    "TodaysPeakDemandTS": "20220129000040",
    "Unloaded_capacity_4H": 13526,
    "Unloaded_capacity_10M": 8360,
    "currentRenewables": 3381,
    "Limitation": "2990.98",
    "PS_VERSION": "1.26b",
    "AvailableCapacity": 38273,
    "renewablesPercent": 16,
    "CurrentAdjustedUnloadedGenerationCapacityTS": "20220129051956",
    "todayForecastPeakDemandTS": "20220129183000",
    "currentCo2intensity": 0.3384014243941891,
    "todayForecastPeakDemand": 25694,
    "currentSolar": -42,
    "CurrentSystemDemand": 21493,
    "currentCo2": 7273,
    "CurrentAdjustedUnloadedGenerationCapacity": 16780,
    "OutageDTS": "07/17/2019 23:30:00 (PPT)",
    "HistoryFirstDate": "20180410",
    "CurrentNetDemandWithoutPump": 19538,
    "Shutdown": "2501.37",
    "Unloaded_capacity_1H": 12127,
    "Unloaded_capacity_derated_nax": 34026,
    "TodaysPeakDemand": 22490,
    "currentWind": 1680,
    "tomorrowsForecastPeakDemand": 25546,
    "CurrentNetDemandTS": "20220129051811",
    "CurrentNetDemand": 19836,
    "currentRenewableswoBatteries": 3304,
    "gridstatus": [
        "Normal"
    ],
    "Current_reserve": 3024,
    "CurrentSystemDemandWithoutPump": 21248
}
