{
    "todayForecastPeakDemandTS":  "20210326081500",
    "AvailableCapacity":  35874,
    "currentWind":  1975,
    "Limitation":  0,
    "CurrentSystemDemandWithoutPump":  20199,
    "histDemand":  "50,270 MW",
    "TodaysPeakDemand":  25563,
    "slotDate":  "03/26/2021 11:15",
    "gridstatus":  [
                       "Normal"
                   ],
    "currentCo2intensity":  0.11422662815439012,
    "CurrentNetDemandWithoutPump":  6386,
    "histDemandDate":  "Jul 24, 2006",
    "CurrentNetDemand":  6775,
    "CurrentSystemDemand":  20607,
    "Shutdown":  0,
    "HistoryFirstDate":  "20180410",
    "CurrentAdjustedUnloadedGenerationCapacityTS":  "20210326111456",
    "CurrentSystemDemandWithoutPumpTS":  "20210326111411",
    "currentRenewableswoBatteries":  15503,
    "TodaysPeakDemandTS":  "20210326075348",
    "currentRenewables":  15511,
    "CurrentNetDemandTS":  "20210326111411",
    "CurrentAdjustedUnloadedGenerationCapacity":  15267,
    "renewablesPercent":  75,
    "CurrentNetDemandWithoutPumpTS":  "20210326111411",
    "tomorrowsForecastPeakDemand":  23899,
    "PS_VERSION":  "1.26b",
    "CurrentSystemDemandTS":  null,
    "currentSolar":  11851,
    "renewablesPercentwoBatteries":  75,
    "OutageDTS":  null,
    "currentCo2":  2354,
    "todayForecastPeakDemand":  25220
}
