{
    "todayForecastPeakDemandTS": "20210321194500",
    "AvailableCapacity": 34107,
    "currentWind": 3097,
    "Limitation": 0,
    "CurrentSystemDemandWithoutPump": 19871,
    "histDemand": "50,270 MW",
    "TodaysPeakDemand": 20836,
    "slotDate": "03/21/2021 06:05",
    "gridstatus": [
        "Normal"
    ],
    "currentCo2intensity": 0.2941207294402338,
    "CurrentNetDemandWithoutPump": 16732,
    "histDemandDate": "Jul 24, 2006",
    "CurrentNetDemand": 16868,
    "CurrentSystemDemand": 19890,
    "Shutdown": 0,
    "HistoryFirstDate": "20180410",
    "CurrentAdjustedUnloadedGenerationCapacityTS": "20210321060456",
    "CurrentSystemDemandWithoutPumpTS": "20210321060411",
    "currentRenewableswoBatteries": 4726,
    "TodaysPeakDemandTS": "20210321000048",
    "currentRenewables": 4626,
    "CurrentNetDemandTS": "20210321060411",
    "CurrentAdjustedUnloadedGenerationCapacity": 14217,
    "renewablesPercent": 23,
    "CurrentNetDemandWithoutPumpTS": "20210321060411",
    "tomorrowsForecastPeakDemand": 25904,
    "PS_VERSION": "1.26b",
    "CurrentSystemDemandTS": null,
    "currentSolar": -43,
    "renewablesPercentwoBatteries": 24,
    "OutageDTS": null,
    "currentCo2": 5850,
    "todayForecastPeakDemand": 23938
}
