{
    "Unloaded_capacity_derated_max":  39279,
    "todayForecastPeakDemand":  25847,
    "Unloaded_capacity_1H":  11926,
    "Shutdown":  "2501.37",
    "currentRenewablesHybrid":  null,
    "CurrentSystemDemandWithoutPump":  18105,
    "Required_reserve":  1542,
    "currentCoalCO2":  0,
    "Current_reserve":  2554,
    "currentBiomassCO2":  120,
    "currentOther":  0.0,
    "HistoryFirstDate":  "20180410",
    "currentNuclear":  1144,
    "currentGeothermal":  776,
    "tomorrowsForecastPeakDemand":  24120,
    "Limitation":  "2990.98",
    "currentSolar":  18001,
    "TodaysPeakDemandTS":  "20240503085812",
    "currentImports":  -3388,
    "currentNaturalGasCO2":  961,
    "CurrentAdjustedUnloadedGenerationCapacityTS":  "20240503125456",
    "currentBiogasCO2":  91,
    "currentSolarHybrids":  1263,
    "Unloaded_capacity_10M":  8328,
    "currentRenewables":  21855,
    "currentWindHybrids":  0.0,
    "currentCo2":  -308,
    "currentImportsCO2":  -1473,
    "CurrentSystemDemandWithoutPumpTS":  "20240503125411",
    "Available_capacity":  31554,
    "todayForecastPeakDemandTS":  "20240503203000",
    "currentLargeHydro":  1034,
    "CurrentNetDemandWithoutPumpTS":  "20240503125411",
    "CurrentNetDemandWithoutPump":  -944,
    "hybridsPercent":  4.4,
    "currentWind":  2400,
    "currentGeothermalCO2":  7,
    "CurrentSystemDemand":  23226,
    "currentBiomass":  272,
    "currentNonRenewableHybrid":  null,
    "CurrentSystemDemandTS":  "20240503125456",
    "currentNaturalGas":  2169,
    "histDemand":  "52,061 MW",
    "histDemandDate":  "Sep 6, 2022",
    "CurrentAdjustedUnloadedGenerationCapacity":  23571,
    "CurrentSystemDemandPlusUnloaded4h":  44140,
    "gridstatus":  [
                       "Normal"
                   ],
    "slotDate":  "05/03/2024 12:55",
    "renewablesPercentwoBatteries":  94,
    "currentBatteriesStandalone":  -4244,
    "currentCoal":  0,
    "currentBiogas":  173,
    "currentBatteriesHybrid":  -235,
    "currentSmallHydro":  271,
    "AvailableCapacity":  46797,
    "currentHybrids":  1016,
    "PS_VERSION":  "1.26b",
    "Unloaded_capacity_4H":  20914,
    "renewablesPercent":  94,
    "CurrentNetDemand":  4129,
    "currentBatteries":  -4488,
    "CurrentNetDemandTS":  "20240503125411",
    "OutageDTS":  "07/17/2019 23:30:00 (PPT)",
    "currentRenewableswoBatteries":  21855,
    "currentCo2intensity":  -0.0132577809944436943905460263,
    "TodaysPeakDemand":  25549
}
