{
    "CurrentNetDemandWithoutPumpTS":  "20230129105411",
    "slotDate":  "01/29/2023 10:55",
    "renewablesPercentwoBatteries":  63,
    "histDemand":  "52,061 MW",
    "CurrentSystemDemandWithoutPumpTS":  "20230129105411",
    "Unloaded_capacity_derated_max":  37456,
    "histDemandDate":  "Sep 08, 2022",
    "Required_reserve":  1371,
    "CurrentSystemDemandTS":  "20230129105456",
    "TodaysPeakDemandTS":  "20230129100200",
    "Unloaded_capacity_4H":  18291,
    "Unloaded_capacity_10M":  7695,
    "currentRenewables":  16343,
    "Limitation":  "2990.98",
    "PS_VERSION":  "1.26b",
    "AvailableCapacity":  44031,
    "renewablesPercent":  68,
    "CurrentAdjustedUnloadedGenerationCapacityTS":  "20230129105456",
    "todayForecastPeakDemandTS":  "20230129183000",
    "currentCo2intensity":  0.176249672291209159639917523,
    "todayForecastPeakDemand":  27149,
    "currentSolar":  10202,
    "CurrentSystemDemand":  23861,
    "currentCo2":  4206,
    "CurrentAdjustedUnloadedGenerationCapacity":  20170,
    "OutageDTS":  "07/17/2019 23:30:00 (PPT)",
    "HistoryFirstDate":  "20180410",
    "Available_capacity":  31556,
    "CurrentNetDemandWithoutPump":  7505,
    "CurrentSystemDemandPlusUnloaded4h":  42152,
    "Shutdown":  "2501.37",
    "Unloaded_capacity_1H":  12094,
    "TodaysPeakDemand":  24502,
    "currentWind":  3136,
    "tomorrowsForecastPeakDemand":  28863.0,
    "CurrentNetDemandTS":  "20230129105411",
    "CurrentNetDemand":  10620,
    "currentRenewableswoBatteries":  14989,
    "gridstatus":  [
                       "Normal"
                   ],
    "Current_reserve":  2039,
    "CurrentSystemDemandWithoutPump":  20753
}
