{
    "Unloaded_capacity_derated_max":  29757,
    "todayForecastPeakDemand":  34398,
    "Unloaded_capacity_1H":  11293,
    "Shutdown":  "2501.37",
    "currentRenewablesHybrid":  null,
    "CurrentSystemDemandWithoutPump":  24702,
    "Required_reserve":  1399,
    "currentCoalCO2":  0.0,
    "Current_reserve":  2140,
    "currentBiomassCO2":  142,
    "currentOther":  0,
    "HistoryFirstDate":  "20180410",
    "currentNuclear":  2217,
    "currentGeothermal":  849,
    "tomorrowsForecastPeakDemand":  34966,
    "Limitation":  "2990.98",
    "currentSolar":  7,
    "TodaysPeakDemandTS":  "20230907000048",
    "currentImports":  5703,
    "currentNaturalGasCO2":  4837,
    "CurrentAdjustedUnloadedGenerationCapacityTS":  "20230907005456",
    "currentBiogasCO2":  110,
    "currentSolarHybrids":  -3,
    "Unloaded_capacity_10M":  7314,
    "currentRenewables":  4500,
    "currentWindHybrids":  0.0,
    "currentCo2":  7552,
    "currentImportsCO2":  2414,
    "CurrentSystemDemandWithoutPumpTS":  "20230907005411",
    "Available_capacity":  32533,
    "todayForecastPeakDemandTS":  "20230907184500",
    "currentLargeHydro":  2999,
    "CurrentNetDemandWithoutPumpTS":  "20230907005411",
    "CurrentNetDemandWithoutPump":  21990,
    "hybridsPercent":  0,
    "currentWind":  2751,
    "currentGeothermalCO2":  8,
    "CurrentSystemDemand":  25219,
    "currentBiomass":  336,
    "currentNonRenewableHybrid":  null,
    "CurrentSystemDemandTS":  "20230907005456",
    "currentNaturalGas":  11268,
    "histDemand":  "52,061 MW",
    "histDemandDate":  "Sep 6, 2022",
    "CurrentAdjustedUnloadedGenerationCapacity":  19322,
    "CurrentSystemDemandPlusUnloaded4h":  44448,
    "gridstatus":  [
                       "Normal"
                   ],
    "slotDate":  "09/07/2023 00:55",
    "renewablesPercentwoBatteries":  18,
    "currentBatteriesStandalone":  -576,
    "currentCoal":  0.0,
    "currentBiogas":  218,
    "currentBatteriesHybrid":  -2,
    "currentSmallHydro":  359,
    "AvailableCapacity":  44541,
    "currentHybrids":  11,
    "PS_VERSION":  "1.26b",
    "Unloaded_capacity_4H":  19229,
    "renewablesPercent":  18,
    "CurrentNetDemand":  22471,
    "currentBatteries":  -578,
    "CurrentNetDemandTS":  "20230907005411",
    "OutageDTS":  "07/17/2019 23:30:00 (PPT)",
    "currentRenewableswoBatteries":  4500,
    "currentCo2intensity":  0.2994773711103717999402823384,
    "TodaysPeakDemand":  26214
}
