{
    "todayForecastPeakDemandTS": "20210707183000",
    "AvailableCapacity": 49898,
    "currentWind": 2029,
    "Limitation": 0,
    "CurrentSystemDemandWithoutPump": 35029,
    "histDemand": "50,270 MW",
    "TodaysPeakDemand": 35077,
    "slotDate": "07/07/2021 15:40",
    "gridstatus": [
        "Normal"
    ],
    "currentCo2intensity": 0.20374573469939244,
    "CurrentNetDemandWithoutPump": 21044,
    "histDemandDate": "Jul 24, 2006",
    "CurrentNetDemand": 21102,
    "CurrentSystemDemand": 35071,
    "Shutdown": 0,
    "HistoryFirstDate": "20180410",
    "CurrentAdjustedUnloadedGenerationCapacityTS": "20210707153957",
    "CurrentSystemDemandWithoutPumpTS": "20210707153811",
    "currentRenewableswoBatteries": 15634,
    "TodaysPeakDemandTS": "20210707153952",
    "currentRenewables": 15659,
    "CurrentNetDemandTS": "20210707153811",
    "CurrentAdjustedUnloadedGenerationCapacity": 14827,
    "renewablesPercent": 45,
    "CurrentNetDemandWithoutPumpTS": "20210707153811",
    "tomorrowsForecastPeakDemand": 40334,
    "PS_VERSION": "1.26b",
    "CurrentSystemDemandTS": null,
    "currentSolar": 11924,
    "renewablesPercentwoBatteries": 45,
    "OutageDTS": null,
    "currentCo2": 7145,
    "todayForecastPeakDemand": 37541
}
