{
    "CurrentNetDemandWithoutPumpTS":  "20220731112411",
    "slotDate":  "07/31/2022 11:25",
    "renewablesPercentwoBatteries":  48,
    "histDemand":  "50,270 MW",
    "CurrentSystemDemandWithoutPumpTS":  "20220731112411",
    "Unloaded_capacity_derated_max":  31606,
    "histDemandDate":  "Jul 24, 2006",
    "Required_reserve":  1732,
    "CurrentSystemDemandTS":  "20220731112456",
    "TodaysPeakDemandTS":  "20220731111948",
    "Unloaded_capacity_4H":  17919,
    "Unloaded_capacity_10M":  9037,
    "currentRenewables":  14652,
    "Limitation":  "2990.98",
    "PS_VERSION":  "1.26b",
    "AvailableCapacity":  50769,
    "renewablesPercent":  50,
    "CurrentAdjustedUnloadedGenerationCapacityTS":  "20220731112456",
    "todayForecastPeakDemandTS":  "20220731183000",
    "currentCo2intensity":  0.2083080797687919171887095571,
    "todayForecastPeakDemand":  36089,
    "currentSolar":  11257,
    "CurrentSystemDemand":  29351,
    "currentCo2":  6114,
    "CurrentAdjustedUnloadedGenerationCapacity":  21418,
    "OutageDTS":  "07/17/2019 23:30:00 (PPT)",
    "HistoryFirstDate":  "20180410",
    "Available_capacity":  38388,
    "CurrentNetDemandWithoutPump":  15151,
    "CurrentSystemDemandPlusUnloaded4h":  47270,
    "Shutdown":  "2501.37",
    "Unloaded_capacity_1H":  13578,
    "TodaysPeakDemand":  29352,
    "currentWind":  1282,
    "tomorrowsForecastPeakDemand":  39564.0,
    "CurrentNetDemandTS":  "20220731112411",
    "CurrentNetDemand":  16804,
    "currentRenewableswoBatteries":  14138,
    "gridstatus":  [
                       "Normal"
                   ],
    "Current_reserve":  2425,
    "CurrentSystemDemandWithoutPump":  27706
}
