{
    "CurrentNetDemandWithoutPumpTS": "20220922143811",
    "slotDate": "09/22/2022 14:40",
    "renewablesPercentwoBatteries": 55,
    "histDemand": "52,061 MW",
    "CurrentSystemDemandWithoutPumpTS": "20220922143811",
    "Unloaded_capacity_derated_max": 34834,
    "histDemandDate": "Sep 08, 2022",
    "Required_reserve": 1654,
    "CurrentSystemDemandTS": "20220922143956",
    "TodaysPeakDemandTS": "20220922143956",
    "Unloaded_capacity_4H": 18605,
    "Unloaded_capacity_10M": 10294,
    "currentRenewables": 15008,
    "Limitation": "2990.98",
    "PS_VERSION": "1.26b",
    "AvailableCapacity": 51067,
    "renewablesPercent": 53,
    "CurrentAdjustedUnloadedGenerationCapacityTS": "20220922143956",
    "todayForecastPeakDemandTS": "20220922193000",
    "currentCo2intensity": 0.16665015184848425,
    "todayForecastPeakDemand": 31332,
    "currentSolar": 12788,
    "CurrentSystemDemand": 28055,
    "currentCo2": 4675,
    "CurrentAdjustedUnloadedGenerationCapacity": 23012,
    "OutageDTS": "07/17/2019 23:30:00 (PPT)",
    "HistoryFirstDate": "20180410",
    "Available_capacity": 38349,
    "CurrentNetDemandWithoutPump": 12644,
    "CurrentSystemDemandPlusUnloaded4h": 46660,
    "Shutdown": "2501.37",
    "Unloaded_capacity_1H": 14094,
    "TodaysPeakDemand": 28055,
    "currentWind": 1139,
    "tomorrowsForecastPeakDemand": 34597.0,
    "CurrentNetDemandTS": "20220922143811",
    "CurrentNetDemand": 14030,
    "currentRenewableswoBatteries": 15524,
    "gridstatus": [
        "Normal"
    ],
    "Current_reserve": 2699,
    "CurrentSystemDemandWithoutPump": 26627
}
