{
    "Unloaded_capacity_derated_max":  35946,
    "todayForecastPeakDemand":  25745,
    "Unloaded_capacity_1H":  9187,
    "Shutdown":  "2501.37",
    "currentRenewablesHybrid":  null,
    "CurrentSystemDemandWithoutPump":  24625,
    "Required_reserve":  1412,
    "currentCoalCO2":  0,
    "Current_reserve":  1970,
    "currentBiomassCO2":  44,
    "currentOther":  0.0,
    "HistoryFirstDate":  "20180410",
    "currentNuclear":  1139,
    "currentGeothermal":  768,
    "tomorrowsForecastPeakDemand":  25155,
    "Limitation":  "2990.98",
    "currentSolar":  24,
    "TodaysPeakDemandTS":  "20240424202156",
    "currentImports":  4659,
    "currentNaturalGasCO2":  1970,
    "CurrentAdjustedUnloadedGenerationCapacityTS":  "20240424214456",
    "currentBiogasCO2":  83,
    "currentSolarHybrids":  -2,
    "Unloaded_capacity_10M":  6089,
    "currentRenewables":  5924,
    "currentWindHybrids":  0.0,
    "currentCo2":  4187,
    "currentImportsCO2":  2167,
    "CurrentSystemDemandWithoutPumpTS":  "20240424214411",
    "Available_capacity":  31239,
    "todayForecastPeakDemandTS":  "20240424203000",
    "currentLargeHydro":  4712,
    "CurrentNetDemandWithoutPumpTS":  "20240424214411",
    "CurrentNetDemandWithoutPump":  19971,
    "hybridsPercent":  0.6,
    "currentWind":  4650,
    "currentGeothermalCO2":  8,
    "CurrentSystemDemand":  25149,
    "currentBiomass":  91,
    "currentNonRenewableHybrid":  null,
    "CurrentSystemDemandTS":  "20240424214456",
    "currentNaturalGas":  4174,
    "histDemand":  "52,061 MW",
    "histDemandDate":  "Sep 6, 2022",
    "CurrentAdjustedUnloadedGenerationCapacity":  16909,
    "CurrentSystemDemandPlusUnloaded4h":  38716,
    "gridstatus":  [
                       "Normal"
                   ],
    "slotDate":  "04/24/2024 21:45",
    "renewablesPercentwoBatteries":  24,
    "currentBatteriesStandalone":  3457,
    "currentCoal":  0,
    "currentBiogas":  148,
    "currentBatteriesHybrid":  137,
    "currentSmallHydro":  266,
    "AvailableCapacity":  42058,
    "currentHybrids":  159,
    "PS_VERSION":  "1.26b",
    "Unloaded_capacity_4H":  13567,
    "renewablesPercent":  24,
    "CurrentNetDemand":  20522,
    "currentBatteries":  3652,
    "CurrentNetDemandTS":  "20240424214411",
    "OutageDTS":  "07/17/2019 23:30:00 (PPT)",
    "currentRenewableswoBatteries":  5924,
    "currentCo2intensity":  0.1664876342466366310799263371,
    "TodaysPeakDemand":  25739
}
