{
    "CurrentNetDemandWithoutPumpTS":  "20211227002411",
    "slotDate":  "12/27/2021 00:25",
    "renewablesPercentwoBatteries":  25,
    "histDemand":  "50,270 MW",
    "CurrentSystemDemandWithoutPumpTS":  "20211227002411",
    "Available_capacity":  30582,
    "histDemandDate":  "Jul 24, 2006",
    "Required_reserve":  1183,
    "CurrentSystemDemandTS":  "20211227002456",
    "TodaysPeakDemandTS":  "20211227000220",
    "Unloaded_capacity_4H":  13388,
    "Unloaded_capacity_10M":  8604,
    "currentRenewables":  5917,
    "Limitation":  "2990.98",
    "PS_VERSION":  "1.26b",
    "AvailableCapacity":  40713,
    "renewablesPercent":  27,
    "CurrentAdjustedUnloadedGenerationCapacityTS":  "20211227002456",
    "todayForecastPeakDemandTS":  "20211227183000",
    "currentCo2intensity":  0.3020951519321030387858371632,
    "todayForecastPeakDemand":  29860,
    "currentSolar":  -35,
    "CurrentSystemDemand":  21979,
    "currentCo2":  6640,
    "CurrentAdjustedUnloadedGenerationCapacity":  18734,
    "OutageDTS":  "07/17/2019 23:30:00 (PPT)",
    "HistoryFirstDate":  "20180410",
    "CurrentNetDemandWithoutPump":  17645,
    "Shutdown":  "2501.37",
    "Unloaded_capacity_1H":  12131,
    "Unloaded_capacity_derated_nax":  33539,
    "TodaysPeakDemand":  22393,
    "currentWind":  3986,
    "tomorrowsForecastPeakDemand":  30712,
    "CurrentNetDemandTS":  "20211227002411",
    "CurrentNetDemand":  18055,
    "currentRenewableswoBatteries":  5495,
    "gridstatus":  [
                       "Normal"
                   ],
    "Current_reserve":  2101,
    "CurrentSystemDemandWithoutPump":  21504
}
