{
    "Unloaded_capacity_derated_max":  35558,
    "todayForecastPeakDemand":  36403,
    "Unloaded_capacity_1H":  13198,
    "Shutdown":  "2501.37",
    "currentRenewablesHybrid":  null,
    "CurrentSystemDemandWithoutPump":  27788,
    "Required_reserve":  1716,
    "currentCoalCO2":  -2,
    "Current_reserve":  2916,
    "currentBiomassCO2":  142,
    "currentOther":  0,
    "HistoryFirstDate":  "20180410",
    "currentNuclear":  2250,
    "currentGeothermal":  804,
    "tomorrowsForecastPeakDemand":  35344,
    "Limitation":  "2990.98",
    "currentSolar":  12727,
    "TodaysPeakDemandTS":  "20230809092124",
    "currentImports":  3666,
    "currentNaturalGasCO2":  3361,
    "CurrentAdjustedUnloadedGenerationCapacityTS":  "20230809094956",
    "currentBiogasCO2":  112,
    "currentSolarHybrids":  440,
    "Unloaded_capacity_10M":  9206,
    "currentRenewables":  16683,
    "currentWindHybrids":  5,
    "currentCo2":  5454,
    "currentImportsCO2":  1656,
    "CurrentSystemDemandWithoutPumpTS":  "20230809094811",
    "Available_capacity":  38705,
    "todayForecastPeakDemandTS":  "20230809184500",
    "currentLargeHydro":  2169,
    "CurrentNetDemandWithoutPumpTS":  "20230809094811",
    "CurrentNetDemandWithoutPump":  13163,
    "hybridsPercent":  0.7,
    "currentWind":  2326,
    "currentGeothermalCO2":  7,
    "CurrentSystemDemand":  29499,
    "currentBiomass":  322,
    "currentNonRenewableHybrid":  null,
    "CurrentSystemDemandTS":  "20230809094956",
    "currentNaturalGas":  7730,
    "histDemand":  "52,061 MW",
    "histDemandDate":  "Sep 6, 2022",
    "CurrentAdjustedUnloadedGenerationCapacity":  23567,
    "CurrentSystemDemandPlusUnloaded4h":  50997,
    "gridstatus":  [
                       "Normal"
                   ],
    "slotDate":  "08/09/2023 09:50",
    "renewablesPercentwoBatteries":  57,
    "currentBatteriesStandalone":  -1653,
    "currentCoal":  -2,
    "currentBiogas":  216,
    "currentBatteriesHybrid":  -253,
    "currentSmallHydro":  379,
    "AvailableCapacity":  53066,
    "currentHybrids":  193,
    "PS_VERSION":  "1.26b",
    "Unloaded_capacity_4H":  21498,
    "renewablesPercent":  57,
    "CurrentNetDemand":  14863,
    "currentBatteries":  -1827,
    "CurrentNetDemandTS":  "20230809094811",
    "OutageDTS":  "07/17/2019 23:30:00 (PPT)",
    "currentRenewableswoBatteries":  16683,
    "currentCo2intensity":  0.1849038778728939003140486134,
    "TodaysPeakDemand":  30184
}
